README.md
setup.py
aws_sync/__init__.py
aws_sync/main.py
aws_sync.egg-info/PKG-INFO
aws_sync.egg-info/SOURCES.txt
aws_sync.egg-info/dependency_links.txt
aws_sync.egg-info/requires.txt
aws_sync.egg-info/top_level.txt