Metadata-Version: 1.0
Name: aws-sync
Version: 0.3
Summary: Sync AWS secrets across multiple accounts
Home-page: https://github.com/UdhavPawar/aws_sync
Author: Udhav Pawar
Author-email: upawar78@gmail.com
License: MIT
Keywords: aws,secrets,aws-secrets-manager,aws-sync,replicate,credentials,automation
Platform: UNKNOWN
